wikiblame.py
wikiblame-1.0.2.dist-info/licenses/license.md
wikiblame-1.0.2.dist-info/METADATA
wikiblame-1.0.2.dist-info/WHEEL
wikiblame-1.0.2.dist-info/entry_points.txt
wikiblame-1.0.2.dist-info/top_level.txt
wikiblame-1.0.2.dist-info/RECORD
