Metadata-Version: 2.4
Name: wikiblame
Version: 1.0.2
Summary: Convert a wikipedia article to a git repository
Author-email: Jordi Burguet-Castell <jordi.burguet.castell@gmail.com>
License-Expression: GPL-3.0-or-later
Project-URL: Homepage, https://gitlab.com/jordibc/wikiblame
Classifier: Programming Language :: Python :: 3
Requires-Python: >=3.7
License-File: license.md
Requires-Dist: mwclient
Dynamic: license-file
